weatherlinkv2/__init__.py
weatherlinkv2/api.py
weatherlinkv2/utils.py
weatherlinkv2-0.1.2.dist-info/licenses/LICENSE
weatherlinkv2-0.1.2.dist-info/METADATA
weatherlinkv2-0.1.2.dist-info/WHEEL
weatherlinkv2-0.1.2.dist-info/top_level.txt
weatherlinkv2-0.1.2.dist-info/RECORD
