Metadata-Version: 2.4
Name: weatherlinkv2
Version: 0.1.2
Summary: Professional Python library for WeatherLink v2 API integration
Author-email: Nicolas Mantilla-Molina <nicomantimol1@gmail.com>
License: CC-BY-NC-SA-4.0
Project-URL: Homepage, https://github.com/Vendetta0462/weatherlinkv2
Project-URL: Repository, https://github.com/Vendetta0462/weatherlinkv2
Project-URL: Bug Tracker, https://github.com/Vendetta0462/weatherlinkv2/issues
Keywords: weather,meteorology,weatherlink,api,climate,atmospheric,air quality,environmental monitoring
Classifier: Development Status :: 4 - Beta
Classifier: Intended Audience :: Developers
Classifier: Intended Audience :: Science/Research
Classifier: Intended Audience :: Education
Classifier: Topic :: Scientific/Engineering :: Atmospheric Science
Classifier: Topic :: Software Development :: Libraries :: Python Modules
Classifier: License :: Other/Proprietary License
Classifier: Programming Language :: Python :: 3
Classifier: Programming Language :: Python :: 3.7
Classifier: Programming Language :: Python :: 3.8
Classifier: Programming Language :: Python :: 3.9
Classifier: Programming Language :: Python :: 3.10
Classifier: Programming Language :: Python :: 3.11
Classifier: Programming Language :: Python :: 3.12
Classifier: Operating System :: OS Independent
Classifier: Natural Language :: English
Requires-Python: >=3.7
License-File: LICENSE
Requires-Dist: requests>=2.25.0
Requires-Dist: pandas>=1.3.0
Requires-Dist: matplotlib>=3.3.0
Requires-Dist: seaborn>=0.11.0
Requires-Dist: python-dotenv>=0.19.0
Provides-Extra: dev
Requires-Dist: pytest>=6.0; extra == "dev"
Requires-Dist: pytest-cov>=2.0; extra == "dev"
Requires-Dist: black>=21.0; extra == "dev"
Requires-Dist: flake8>=3.8; extra == "dev"
Requires-Dist: mypy>=0.900; extra == "dev"
Provides-Extra: viz
Requires-Dist: plotly>=5.0; extra == "viz"
Requires-Dist: seaborn>=0.11; extra == "viz"
Provides-Extra: jupyter
Requires-Dist: jupyter>=1.0; extra == "jupyter"
Requires-Dist: ipywidgets>=7.6; extra == "jupyter"
Dynamic: license-file
